LICENSE.txt
MANIFEST.in
README.rst
setup.py
D:/TAcase/BravoTool/troubleShooting/src/bin/pyts
D:/TAcase/BravoTool/troubleShooting/src/bin/pyts.bat
D:/TAcase/BravoTool/troubleShooting/src/bin/pytsmgr
D:/TAcase/BravoTool/troubleShooting/src/bin/pytsmgr.bat
src/bin/pyts
src/bin/pyts.bat
src/bin/pytsmgr
src/bin/pytsmgr.bat
src/troubleshooting/__init__.py
src/troubleshooting/framework/__init__.py
src/troubleshooting/framework/conf/__init__.py
src/troubleshooting/framework/conf/init.conf
src/troubleshooting/framework/exception/__init__.py
src/troubleshooting/framework/exception/exception.py
src/troubleshooting/framework/httpserver/CGIHTTPServer.py
src/troubleshooting/framework/httpserver/__init__.py
src/troubleshooting/framework/httpserver/server.py
src/troubleshooting/framework/httpserver/www/__init__.py
src/troubleshooting/framework/httpserver/www/index.html
src/troubleshooting/framework/httpserver/www/list.html
src/troubleshooting/framework/httpserver/www/cgi-bin/__init__.py
src/troubleshooting/framework/httpserver/www/cgi-bin/index.py
src/troubleshooting/framework/httpserver/www/css/__init__.py
src/troubleshooting/framework/httpserver/www/css/demo.css
src/troubleshooting/framework/httpserver/www/css/normalize.css
src/troubleshooting/framework/httpserver/www/css/ns-default.css
src/troubleshooting/framework/httpserver/www/css/ns-style-attached.css
src/troubleshooting/framework/httpserver/www/css/ns-style-bar.css
src/troubleshooting/framework/httpserver/www/css/ns-style-growl.css
src/troubleshooting/framework/httpserver/www/css/ns-style-other.css
src/troubleshooting/framework/httpserver/www/css/style.css
src/troubleshooting/framework/httpserver/www/fonts/__init__.py
src/troubleshooting/framework/httpserver/www/fonts/codropsicons/__init__.py
src/troubleshooting/framework/httpserver/www/fonts/codropsicons/codropsicons.eot
src/troubleshooting/framework/httpserver/www/fonts/codropsicons/codropsicons.svg
src/troubleshooting_framework.egg-info/PKG-INFO
src/troubleshooting_framework.egg-info/SOURCES.txt
src/troubleshooting_framework.egg-info/dependency_links.txt
src/troubleshooting_framework.egg-info/requires.txt
src/troubleshooting_framework.egg-info/top_level.txt