Metadata-Version: 1.1
Name: troubleshooting-framework
Version: 1.3.1.3
Summary: This is an troubleShooting Framework Package
Home-page: https://github.com/gaoxiaofeng/troubleShooting
Author: Gao Xiao Feng
Author-email: zeus.gao@foxmail.com
License: Apache License 2.0
Keywords: troubleshooting gaoxiaofeng
Platform: UNKNOWN
Classifier: Development Status :: 5 - Production/Stable
Classifier: License :: OSI Approved :: Apache Software License
Classifier: Operating System :: OS Independent
Classifier: Programming Language :: Python
Classifier: Topic :: Software Development :: Testing
